discern/__init__.py
discern/__main__.py
discern/_config.py
discern/_scripts/__init__.py
discern/_scripts/merge_parameters.py
discern/estimators/__init__.py
discern/estimators/batch_integration.py
discern/estimators/callbacks.py
discern/estimators/customlayers.py
discern/estimators/losses.py
discern/estimators/run_exp.py
discern/estimators/utilities_wae.py
discern/functions.py
discern/io.py
discern/mmd/__init__.py
discern/mmd/_cmmd.c
discern/mmd/_cmmd.h
discern/mmd/_mmd.pyx
discern/mmd/mmd.py
discern/online_learning.py
discern/preprocessing.py
discern/mmd/_mmd.c
discern/mmd/_mmd.cpython-36m-x86_64-linux-gnu.so
discern_reconstruction-0.1.1.dist-info/entry_points.txt
discern_reconstruction-0.1.1.dist-info/LICENSE
discern_reconstruction-0.1.1.dist-info/WHEEL
discern_reconstruction-0.1.1.dist-info/METADATA
discern_reconstruction-0.1.1.dist-info/RECORD
