Metadata-Version: 2.1
Name: discern-reconstruction
Version: 0.1.1
Summary: Wasserstein Auto-Encoder for expression reconstruction
Home-page: https://discern.readthedocs.io/en/latest/quickinfo.html
License: MIT
Author: Fabian Hausmann
Author-email: fabian.hausmann@zmnh.uni-hamburg.de
Requires-Python: >=3.6.9,<4.0.0
Classifier: License :: OSI Approved :: MIT License
Classifier: Programming Language :: Python :: 3
Classifier: Programming Language :: Python :: 3.10
Classifier: Programming Language :: Python :: 3.7
Classifier: Programming Language :: Python :: 3.8
Classifier: Programming Language :: Python :: 3.9
Provides-Extra: doc
Provides-Extra: jupyter
Requires-Dist: Cython (>=0.29.16,<0.30.0)
Requires-Dist: Sphinx (>=4.1.1,<5.0.0); extra == "doc"
Requires-Dist: click (>=7.1.2,<8.0.0)
Requires-Dist: hyperopt (>=0.2.3,<0.3.0)
Requires-Dist: ipykernel (>=5.5.0,<6.0.0); extra == "jupyter"
Requires-Dist: joblib (>=1.0.1,<2.0.0)
Requires-Dist: llvmlite (<0.35.0)
Requires-Dist: ray[tune,default] (>=1.6.0,<1.7.0)
Requires-Dist: scanpy (>=1.6.0,<2.0.0)
Requires-Dist: scikit-learn (>=0.23.1,<0.24.0)
Requires-Dist: sphinx-rtd-theme (>=0.5.2,<0.6.0); extra == "doc"
Requires-Dist: tensorflow (==2.1.0)
Requires-Dist: tensorflow-addons (>=0.7.1,<0.8.0)
Requires-Dist: toml (>=0.10.2,<0.11.0); extra == "doc"
Project-URL: Repository, https://github.com/imsb-uke/discern
